wikitrad/__init__.py
wikitrad/wikitrad.py
wikitrad-0.2.0.dist-info/entry_points.txt
wikitrad-0.2.0.dist-info/WHEEL
wikitrad-0.2.0.dist-info/METADATA
wikitrad-0.2.0.dist-info/RECORD
